{
    "B-ACCOUNTNAME": 36,
    "B-ACCOUNTNUMBER": 35,
    "B-AMOUNT": 90,
    "B-BIC": 98,
    "B-BITCOINADDRESS": 64,
    "B-BUILDINGNUMBER": 70,
    "B-CITY": 28,
    "B-COMPANY_NAME": 7,
    "B-COUNTY": 81,
    "B-CREDITCARDCVV": 60,
    "B-CREDITCARDISSUER": 44,
    "B-CREDITCARDNUMBER": 102,
    "B-CURRENCY": 62,
    "B-CURRENCYCODE": 54,
    "B-CURRENCYNAME": 58,
    "B-CURRENCYSYMBOL": 4,
    "B-DATE": 20,
    "B-EMAIL": 95,
    "B-ETHEREUMADDRESS": 53,
    "B-FIRSTNAME": 15,
    "B-FULLNAME": 24,
    "B-IBAN": 49,
    "B-IP": 97,
    "B-IPV4": 25,
    "B-IPV6": 67,
    "B-JOBAREA": 5,
    "B-JOBDESCRIPTOR": 3,
    "B-JOBTITLE": 94,
    "B-JOBTYPE": 46,
    "B-LASTNAME": 43,
    "B-LITECOINADDRESS": 84,
    "B-MAC": 75,
    "B-MASKEDNUMBER": 30,
    "B-MIDDLENAME": 78,
    "B-PASSWORD": 9,
    "B-PHONEIMEI": 74,
    "B-PHONE_NUMBER": 65,
    "B-PIN": 101,
    "B-PREFIX": 1,
    "B-SECONDARYADDRESS": 17,
    "B-SEX": 89,
    "B-SSN": 100,
    "B-STATE": 42,
    "B-STREET": 32,
    "B-STREETADDRESS": 55,
    "B-SUFFIX": 52,
    "B-TIME": 22,
    "B-URL": 47,
    "B-USERAGENT": 39,
    "B-USERNAME": 80,
    "B-VEHICLEVIN": 57,
    "B-VEHICLEVRM": 83,
    "B-ZIPCODE": 33,
    "I-ACCOUNTNAME": 68,
    "I-ACCOUNTNUMBER": 77,
    "I-AMOUNT": 87,
    "I-BIC": 66,
    "I-BITCOINADDRESS": 59,
    "I-BUILDINGNUMBER": 63,
    "I-CITY": 48,
    "I-COMPANY_NAME": 12,
    "I-CREDITCARDCVV": 82,
    "I-CREDITCARDISSUER": 37,
    "I-CREDITCARDNUMBER": 86,
    "I-CURRENCY": 10,
    "I-CURRENCYCODE": 31,
    "I-CURRENCYNAME": 29,
    "I-CURRENCYSYMBOL": 73,
    "I-DATE": 13,
    "I-EMAIL": 14,
    "I-ETHEREUMADDRESS": 2,
    "I-FIRSTNAME": 40,
    "I-FULLNAME": 76,
    "I-IBAN": 85,
    "I-IP": 0,
    "I-IPV4": 51,
    "I-IPV6": 91,
    "I-JOBAREA": 34,
    "I-JOBTITLE": 69,
    "I-JOBTYPE": 16,
    "I-LASTNAME": 61,
    "I-LITECOINADDRESS": 99,
    "I-MAC": 72,
    "I-MASKEDNUMBER": 26,
    "I-MIDDLENAME": 19,
    "I-PASSWORD": 50,
    "I-PHONEIMEI": 11,
    "I-PHONE_NUMBER": 56,
    "I-PIN": 18,
    "I-PREFIX": 23,
    "I-SECONDARYADDRESS": 45,
    "I-SSN": 88,
    "I-STATE": 79,
    "I-STREET": 93,
    "I-STREETADDRESS": 96,
    "I-SUFFIX": 6,
    "I-TIME": 21,
    "I-URL": 8,
    "I-USERAGENT": 27,
    "I-USERNAME": 38,
    "I-VEHICLEVIN": 92,
    "I-VEHICLEVRM": 71,
    "I-ZIPCODE": 41,
    "O": 103
}